sphinxext/presentations/__init__.py
sphinxext/presentations/static/css/reveal.css
sphinxext/presentations/static/js/present.js
sphinxext_presentations-0.3.1.dist-info/LICENSE
sphinxext_presentations-0.3.1.dist-info/METADATA
sphinxext_presentations-0.3.1.dist-info/WHEEL
sphinxext_presentations-0.3.1.dist-info/top_level.txt
sphinxext_presentations-0.3.1.dist-info/RECORD
